AUTHORS
MANIFEST.in
README.rst
setup.py
django_locationstree.egg-info/PKG-INFO
django_locationstree.egg-info/SOURCES.txt
django_locationstree.egg-info/dependency_links.txt
django_locationstree.egg-info/not-zip-safe
django_locationstree.egg-info/requires.txt
django_locationstree.egg-info/top_level.txt
locationstree/__init__.py
locationstree/admin.py
locationstree/conf.py
locationstree/context_processors.py
locationstree/forms.py
locationstree/models.py
locationstree/tests.py
locationstree/urls.py
locationstree/views.py
locationstree/fixtures/chile.json
locationstree/fixtures/sample_locations.json
locationstree/migrations/0001_initial.py
locationstree/migrations/__init__.py
locationstree/templates/locationstree/location_form.html