Metadata-Version: 1.1
Name: django-locationstree
Version: 0.0.0.3
Summary: Simple Django App for location tree
Home-page: https://github.com/witoi/django-locationstree
Author: Witoi.com
Author-email: dev@witoi.com
License: UNKNOWN
Platform: UNKNOWN
Classifier: Topic :: Internet :: WWW/HTTP :: Dynamic Content
Classifier: Intended Audience :: Developers
Classifier: Programming Language :: Python
Classifier: Programming Language :: Python :: 2.7
Classifier: Framework :: Django
Classifier: Development Status :: 1 - Planning
Classifier: Operating System :: OS Independent
